xenget/__init__.py
xenget/xenget.py
xenget-0.0.2.dist-info/LICENSE
xenget-0.0.2.dist-info/METADATA
xenget-0.0.2.dist-info/WHEEL
xenget-0.0.2.dist-info/top_level.txt
xenget-0.0.2.dist-info/RECORD
