Metadata-Version: 2.1
Name: xenget
Version: 0.0.2
Summary: A library for Python to get information from a XenForo forum.
Home-page: UNKNOWN
Author: Cinar Yilmaz
Author-email: <youremail@email.com>
License: GPLv3
Platform: UNKNOWN
Classifier: Programming Language :: Python :: 3
Classifier: License :: OSI Approved :: GNU General Public License v3 (GPLv3)
Classifier: Operating System :: OS Independent
License-File: LICENSE
Requires-Dist: beautifulsoup4
